LICENSE
MANIFEST.in
README.md
setup.py
src/sunhead/__init__.py
src/sunhead/__main__.py
src/sunhead/conf.py
src/sunhead/decorators.py
src/sunhead/exceptions.py
src/sunhead/global_settings.py
src/sunhead/periodical.py
src/sunhead/utils.py
src/sunhead/version.py
src/sunhead.egg-info/PKG-INFO
src/sunhead.egg-info/SOURCES.txt
src/sunhead.egg-info/dependency_links.txt
src/sunhead.egg-info/entry_points.txt
src/sunhead.egg-info/not-zip-safe
src/sunhead.egg-info/requires.txt
src/sunhead.egg-info/top_level.txt
src/sunhead/cli/__init__.py
src/sunhead/cli/abc.py
src/sunhead/cli/banners.py
src/sunhead/cli/entrypoint.py
src/sunhead/cli/helpers.py
src/sunhead/cli/commands/__init__.py
src/sunhead/cli/commands/runserver.py
src/sunhead/events/__init__.py
src/sunhead/events/abc.py
src/sunhead/events/exceptions.py
src/sunhead/events/stream.py
src/sunhead/events/types.py
src/sunhead/events/transports/__init__.py
src/sunhead/events/transports/amqp.py
src/sunhead/events/transports/kafka.py
src/sunhead/metrics/__init__.py
src/sunhead/metrics/factory.py
src/sunhead/metrics/process_collector.py
src/sunhead/rest/__init__.py
src/sunhead/rest/views.py
src/sunhead/serializers/__init__.py
src/sunhead/serializers/json.py
src/sunhead/workers/__init__.py
src/sunhead/workers/abc.py
src/sunhead/workers/stream.py
src/sunhead/workers/http/__init__.py
src/sunhead/workers/http/server.py
src/sunhead/workers/http/ext/__init__.py
src/sunhead/workers/http/ext/runtime.py
src/sunhead/workers/http/ext/stream.py